geotiff_tiler/__init__.py
geotiff_tiler/cli.py
geotiff_tiler/tiler.py
geotiff_tiler_res-0.1.0.dist-info/licenses/LICENSE
geotiff_tiler_res-0.1.0.dist-info/METADATA
geotiff_tiler_res-0.1.0.dist-info/WHEEL
geotiff_tiler_res-0.1.0.dist-info/entry_points.txt
geotiff_tiler_res-0.1.0.dist-info/top_level.txt
geotiff_tiler_res-0.1.0.dist-info/RECORD
