Metadata-Version: 2.4
Name: geotiff_tiler_res
Version: 0.1.0
Summary: A tool to export georeferenced GeoTIFF tiles and labels from raster and classification data.
Home-page: https://github.com/knaxa/geotiff_tiler
Author: potacessium
Author-email: potacessium <kyush.naxa@gmail.com>
License: MIT License
Project-URL: Homepage, https://github.com/knaxa/geotiff_tiler
Project-URL: Repository, https://github.com/knaxa/geotiff_tiler
Project-URL: Issues, https://github.com/knaxa/geotiff_tiler/issues
Requires-Python: >=3.8
License-File: LICENSE
Requires-Dist: numpy>=1.21
Requires-Dist: rasterio>=1.3
Requires-Dist: geopandas>=0.10
Requires-Dist: shapely>=1.8
Requires-Dist: matplotlib>=3.5
Requires-Dist: tqdm>=4.60
Dynamic: author
Dynamic: home-page
Dynamic: license-file
Dynamic: requires-python
